colorcet/.version
colorcet/__init__.py
colorcet/__main__.py
colorcet/plotting.py
colorcet/sineramp.py
colorcet/version.py
colorcet/examples/index.ipynb
colorcet/examples/assets/write_named.py
colorcet/examples/assets/images/census_fire.png
colorcet/examples/assets/images/census_hot.png
colorcet/examples/assets/images/fire.png
colorcet/examples/assets/images/hot.png
colorcet/examples/assets/images/jet.png
colorcet/examples/assets/images/named.png
colorcet/examples/assets/images/rainbow.png
colorcet/examples/assets/images/rainbow4.png
colorcet/examples/user_guide/Categorical.ipynb
colorcet/examples/user_guide/Continuous.ipynb
colorcet/examples/user_guide/index.ipynb
colorcet/tests/__init__.py
colorcet/tests/test_aliases.py
colorcet/tests/test_bokeh.py
colorcet/tests/test_matplotlib.py
colorcet-3.0.1.dist-info/LICENSE.txt
colorcet-3.0.1.dist-info/METADATA
colorcet-3.0.1.dist-info/WHEEL
colorcet-3.0.1.dist-info/entry_points.txt
colorcet-3.0.1.dist-info/top_level.txt
colorcet-3.0.1.dist-info/RECORD
